fastga/__init__.py
fastga/command/__init__.py
fastga/command/api.py
fastga/command/resources/__init__.py
fastga/command/resources/fastga.xml
fastga/command/resources/fastga.yml
fastga/configurations/__init__.py
fastga/configurations/fastga.yml
fastga/conftest.py
fastga/models/__init__.py
fastga/models/aerodynamics/__init__.py
fastga/models/aerodynamics/aero_center.py
fastga/models/aerodynamics/aerodynamics.py
fastga/models/aerodynamics/aerodynamics_high_speed.py
fastga/models/aerodynamics/aerodynamics_low_speed.py
fastga/models/aerodynamics/aerodynamics_stability_derivatives.py
fastga/models/aerodynamics/airfoil_folder/__init__.py
fastga/models/aerodynamics/airfoil_folder/naca0012.af
fastga/models/aerodynamics/airfoil_folder/naca23012.af
fastga/models/aerodynamics/airfoil_folder/naca23015.af
fastga/models/aerodynamics/airfoil_folder/naca23018.af
fastga/models/aerodynamics/airfoil_folder/naca4409.af
fastga/models/aerodynamics/airfoil_folder/naca4412.af
fastga/models/aerodynamics/airfoil_folder/naca4414.af
fastga/models/aerodynamics/airfoil_folder/naca4415.af
fastga/models/aerodynamics/airfoil_folder/naca4420.af
fastga/models/aerodynamics/airfoil_folder/naca4424.af
fastga/models/aerodynamics/airfoil_folder/naca4430.af
fastga/models/aerodynamics/airfoil_folder/naca63_415.af
fastga/models/aerodynamics/airfoil_folder/naca652415.af
fastga/models/aerodynamics/airfoil_folder/roncz.af
fastga/models/aerodynamics/components/__init__.py
fastga/models/aerodynamics/components/airfoil_lift_curve_slope.py
fastga/models/aerodynamics/components/cd0.py
fastga/models/aerodynamics/components/cd0_fuselage.py
fastga/models/aerodynamics/components/cd0_ht.py
fastga/models/aerodynamics/components/cd0_lg.py
fastga/models/aerodynamics/components/cd0_nacelle.py
fastga/models/aerodynamics/components/cd0_other.py
fastga/models/aerodynamics/components/cd0_total.py
fastga/models/aerodynamics/components/cd0_vt.py
fastga/models/aerodynamics/components/cd0_wing.py
fast_oad_cs23-1.3.1.dist-info/AUTHORS.rst
fast_oad_cs23-1.3.1.dist-info/LICENSE.txt
fast_oad_cs23-1.3.1.dist-info/METADATA
fast_oad_cs23-1.3.1.dist-info/WHEEL
fast_oad_cs23-1.3.1.dist-info/entry_points.txt
fast_oad_cs23-1.3.1.dist-info/RECORD
