Metadata-Version: 2.1
Name: FAST-OAD-CS23
Version: 1.3.1
Summary: FAST-OAD-CS23 is a framework for performing rapid Overall Aircraft Design for General Aircraft
Home-page: https://github.com/supaero-aircraft-design/FAST-GA
License: GPL-3.0-only
Keywords: aircraft,design,multi-disciplinary
Author: Florent LUTZ
Author-email: Florent.LUTZ2@isae-supaero.fr
Requires-Python: >=3.8,<3.12
Classifier: Development Status :: 4 - Beta
Classifier: Environment :: Console
Classifier: Intended Audience :: Education
Classifier: Intended Audience :: Science/Research
Classifier: License :: OSI Approved :: GNU General Public License v3 (GPLv3)
Classifier: Natural Language :: English
Classifier: Operating System :: MacOS
Classifier: Operating System :: Microsoft :: Windows
Classifier: Operating System :: POSIX :: Linux
Classifier: Programming Language :: Python :: 3
Classifier: Programming Language :: Python :: 3.8
Classifier: Programming Language :: Python :: 3.9
Classifier: Programming Language :: Python :: 3.10
Classifier: Programming Language :: Python :: 3.11
Classifier: Topic :: Scientific/Engineering :: Physics
Provides-Extra: jupyterlab
Requires-Dist: fast-oad-core (>=1.7,<2.0)
Requires-Dist: jupyterlab (>=3.3.0,<4.0.0) ; extra == "jupyterlab"
Requires-Dist: pyparsing
Requires-Dist: stdatm (>=0.2.0)
